src/__init__.py
src/cli.py
src/server.py
grabba_mcp-0.0.3.dist-info/entry_points.txt
grabba_mcp-0.0.3.dist-info/WHEEL
grabba_mcp-0.0.3.dist-info/METADATA
grabba_mcp-0.0.3.dist-info/RECORD
