Metadata-Version: 2.1
Name: grabba-mcp
Version: 0.0.3
Summary: 
License: Proprietary
Author: Bolu Agbana
Requires-Python: >=3.10,<4.0
Classifier: License :: Other/Proprietary License
Classifier: Programming Language :: Python :: 3
Classifier: Programming Language :: Python :: 3.10
Requires-Dist: fastmcp (>=2.8.0,<3.0.0)
Requires-Dist: grabba (>=0.0.11,<0.0.12)
Requires-Dist: pydantic-settings (>=2.9.1,<3.0.0)
